debugbar/__init__.py
debugbar/debugger.py
debugbar/collectors/DumpCollector.py
debugbar/collectors/KeyValueCollector.py
debugbar/collectors/LogCollector.py
debugbar/collectors/MeasureCollector.py
debugbar/collectors/MessageCollector.py
debugbar/collectors/ModelCollector.py
debugbar/collectors/PythonCollector.py
debugbar/collectors/QueryCollector.py
debugbar/controllers/DebugController.py
debugbar/helpers/css.py
debugbar/helpers/script.py
debugbar/messages/Measure.py
debugbar/messages/Message.py
debugbar/providers/DebugProvider.py
debugbar/providers/__init__.py
debugbar/renderers/JavascriptDebugRenderer.py
debugbar/renderers/TerminalRenderer.py
debugbar/resources/css/tailwind.min.css
debugbar/resources/js/alpine.min.js
debugbar/resources/js/alpine.persist.min.js
debugbar/resources/js/highlight.min.js
debugbar/resources/js/tailwind.min.js
debugbar/scaffold/debug.py
masonite_debugbar-1.0.1.dist-info/LICENSE
masonite_debugbar-1.0.1.dist-info/METADATA
masonite_debugbar-1.0.1.dist-info/WHEEL
masonite_debugbar-1.0.1.dist-info/top_level.txt
masonite_debugbar-1.0.1.dist-info/RECORD
